Metadata-Version: 2.1
Name: sit2standpy
Version: 1.1.3
Summary: Sit-to-stand detection using a single lumbar-mounted accelerometer.
Home-page: https://github.com/PfizerRD/sit2standpy
Author: Lukas Adamowicz
Author-email: lukas.adamowicz@pfizer.com
License: MIT
Download-URL: https://pypi.org/project/sit2standpy/
Project-URL: Documentation, https://sit2standpy.readthedocs.io/en/latest/
Platform: UNKNOWN
Classifier: Programming Language :: Python :: 3
Classifier: License :: OSI Approved :: MIT License
Classifier: Operating System :: OS Independent
Classifier: Topic :: Scientific/Engineering
Classifier: Programming Language :: Python :: 3.7
Requires-Python: >=3.7
Requires-Dist: numpy
Requires-Dist: scipy
Requires-Dist: pandas
Requires-Dist: pywavelets
